factorlogged/__init__.py
factorlogged/databases/database_interface.py
factorlogged/databases/postgres/db.py
factorlogged/databases/postgres/objects.py
factorlogged/middlewares/timestamps.py
factorlogged-0.1.1.dist-info/LICENSE
factorlogged-0.1.1.dist-info/WHEEL
factorlogged-0.1.1.dist-info/METADATA
factorlogged-0.1.1.dist-info/RECORD
